{
  "fetchedAt": "2026-06-05T10:41:07.117Z",
  "currency": "CHF",
  "articles": [
    {
      "title": "Financier Lex Greensill banned from running UK companies for nine years",
      "source": "The Guardian",
      "url": "https://www.theguardian.com/business/2026/jun/04/lex-greensill-banned-uk-companies-nine-years",
      "publishedAt": "2026-06-04T12:42:33Z"
    },
    {
      "title": "EasyJet says US takeover bid would be ‘highly opportunistic’",
      "source": "The Guardian",
      "url": "https://www.theguardian.com/business/2026/jun/01/easyjet-us-takeover-bid-shares-castlelake",
      "publishedAt": "2026-06-01T08:28:40Z"
    },
    {
      "title": "‘How can you have a Ferrari without any vroom?’: electric model shocks owners’ club ",
      "source": "The Guardian",
      "url": "https://www.theguardian.com/business/2026/may/30/ferrari-luce-ev-electric-model-shocks-owners-club",
      "publishedAt": "2026-05-30T04:00:08Z"
    },
    {
      "title": "Bank of England leaves interest rates on hold with committee split 8-1; ECB also keeps rates steady – as it happened",
      "source": "The Guardian",
      "url": "https://www.theguardian.com/business/live/2026/apr/30/bank-of-england-expected-hold-interest-rates-noon-assesses-fallout-iran-war-live-updates",
      "publishedAt": "2026-04-30T14:55:26Z"
    },
    {
      "title": "Air France-KLM cuts capacity growth forecast amid expected $2.4bn fuel bill rise",
      "source": "The Guardian",
      "url": "https://www.theguardian.com/business/2026/apr/30/air-france-klm-cuts-capacity-growth-forecast-amid-expected-24bn-fuel-bill-rise",
      "publishedAt": "2026-04-30T09:13:47Z"
    }
  ]
}