{
  "fetchedAt": "2026-06-19T11:14:24.366Z",
  "currency": "CNY",
  "articles": [
    {
      "title": "UK inflation unexpectedly stays at 2.8% with higher transport costs offset by slower food price rises – as it happened",
      "source": "The Guardian",
      "url": "https://www.theguardian.com/business/live/2026/jun/17/uk-inflation-unexpectedly-unchanged-higher-transport-costs-offset-slower-food-price-rises-oil-federal-reserve-iran-war-live-updates",
      "publishedAt": "2026-06-17T14:19:59Z"
    },
    {
      "title": "EV prices in UK and EU not likely to dive due to Chinese rivalry, says Xpeng boss",
      "source": "The Guardian",
      "url": "https://www.theguardian.com/business/2026/jun/16/ev-prices-uk-eu-chinese-car-firm-xpeng",
      "publishedAt": "2026-06-16T05:00:45Z"
    },
    {
      "title": "EU trade deficit with China reaches record €1bn a day, data shows",
      "source": "The Guardian",
      "url": "https://www.theguardian.com/business/2026/jun/15/eu-trade-deficit-with-china-record-1bn-a-day",
      "publishedAt": "2026-06-15T14:51:39Z"
    },
    {
      "title": "Middle East war is hurting eurozone economy, warns ECB, after announcing first interest rate rise since 2023 – as it happened",
      "source": "The Guardian",
      "url": "https://www.theguardian.com/business/live/2026/jun/11/ryanair-investigation-seating-children-eurozone-interest-rates-middle-east-oil-uk-housing-live-news-updates",
      "publishedAt": "2026-06-11T15:19:17Z"
    },
    {
      "title": "China’s Jingye seeks compensation from UK over British Steel takeover",
      "source": "The Guardian",
      "url": "https://www.theguardian.com/business/2026/jun/11/china-jingye-compensation-uk-british-steel-takeover",
      "publishedAt": "2026-06-11T09:06:12Z"
    }
  ]
}