{
  "fetchedAt": "2026-05-14T09:28:23.278Z",
  "currency": "JPY",
  "articles": [
    {
      "title": "‘There’s a risk of another Liz Truss moment’: City raises spectre of bond market meltdown again",
      "source": "The Guardian",
      "url": "https://www.theguardian.com/business/2026/may/14/theres-a-risk-of-another-liz-truss-moment-city-raises-spectre-of-bond-market-meltdown-again",
      "publishedAt": "2026-05-14T06:00:19Z"
    },
    {
      "title": "Nissan ponders building cars for Chinese rivals at Sunderland plant",
      "source": "The Guardian",
      "url": "https://www.theguardian.com/business/2026/may/13/nissan-ponders-building-cars-for-chinese-rivals-at-sunderland-plant-chery",
      "publishedAt": "2026-05-13T11:54:50Z"
    },
    {
      "title": "UK long-term borrowing costs dip from 28-year high after Starmer allies back PM – as it happened",
      "source": "The Guardian",
      "url": "https://www.theguardian.com/business/live/2026/may/12/uk-bond-yields-borrowing-costs-pound-falls-oil-inflation-live-updates",
      "publishedAt": "2026-05-12T16:23:49Z"
    },
    {
      "title": "UK government borrowing costs rise as Starmer ‘fails to reassure bond markets’ – as it happened",
      "source": "The Guardian",
      "url": "https://www.theguardian.com/business/live/2026/may/11/uk-economy-job-losses-iran-war-oil-pound-bonds-politics-starmer-live-updates",
      "publishedAt": "2026-05-11T16:03:38Z"
    },
    {
      "title": "Iran war costs Toyota £3bn as prices of materials soar and sales fall",
      "source": "The Guardian",
      "url": "https://www.theguardian.com/business/2026/may/08/iran-war-costs-toyota-3bn-prices-materials-soar-sales-fall",
      "publishedAt": "2026-05-08T12:09:58Z"
    }
  ]
}