{
  "fetchedAt": "2026-03-22T07:33:35.968Z",
  "currency": "JPY",
  "articles": [
    {
      "title": "‘It’s stupid’: why western carmakers’ retreat from electric risks dooming them to irrelevance",
      "source": "The Guardian",
      "url": "https://www.theguardian.com/business/2026/mar/21/west-carmakers-retreat-electric-vehicle-risks-irrelevance-iran-war-evs-china",
      "publishedAt": "2026-03-21T12:00:52Z"
    },
    {
      "title": "High charges, poor service: NCP hits the skids as drivers change habits",
      "source": "The Guardian",
      "url": "https://www.theguardian.com/business/2026/mar/20/ncp-car-park-operator-high-charges-administration-debt",
      "publishedAt": "2026-03-20T06:00:11Z"
    },
    {
      "title": "Car park firm NCP falls into administration, putting nearly 700 jobs at risk",
      "source": "The Guardian",
      "url": "https://www.theguardian.com/business/2026/mar/16/car-park-firm-ncp-falls-into-administration-putting-nearly-700-jobs-at-risk",
      "publishedAt": "2026-03-16T18:01:36Z"
    },
    {
      "title": "How high could oil prices go – and what might the global economic fallout be?",
      "source": "The Guardian",
      "url": "https://www.theguardian.com/business/2026/mar/09/how-high-could-oil-go-and-what-might-the-global-economic-fallout-be",
      "publishedAt": "2026-03-09T18:35:50Z"
    },
    {
      "title": "Rachel Reeves warns fuel retailers not to make ‘excess profits’ from oil crisis; G7 ‘stands ready’ to release crude reserves – as it happens",
      "source": "The Guardian",
      "url": "https://www.theguardian.com/business/live/2026/mar/09/stock-markets-plunge-oil-over-100-a-barrel-g7-emergency-oil-reserves-news-updates",
      "publishedAt": "2026-03-09T17:32:08Z"
    }
  ]
}